LICENSE
README.md
pyproject.toml
rootly.egg-info/PKG-INFO
rootly.egg-info/SOURCES.txt
rootly.egg-info/dependency_links.txt
rootly.egg-info/requires.txt
rootly.egg-info/top_level.txt
rootly_sdk/__init__.py
rootly_sdk/client.py
rootly_sdk/errors.py
rootly_sdk/py.typed
rootly_sdk/types.py
rootly_sdk/api/__init__.py
rootly_sdk/api/alert_events/__init__.py
rootly_sdk/api/alert_events/create_alert_event.py
rootly_sdk/api/alert_events/delete_alert_event.py
rootly_sdk/api/alert_events/get_alert_event.py
rootly_sdk/api/alert_events/list_alert_events.py
rootly_sdk/api/alert_events/update_alert_event.py
rootly_sdk/api/alert_fields/__init__.py
rootly_sdk/api/alert_fields/create_alert_field.py
rootly_sdk/api/alert_fields/delete_alert_field.py
rootly_sdk/api/alert_fields/get_alert_field.py
rootly_sdk/api/alert_fields/list_alert_fields.py
rootly_sdk/api/alert_fields/update_alert_field.py
rootly_sdk/api/alert_groups/__init__.py
rootly_sdk/api/alert_groups/create_alert_group.py
rootly_sdk/api/alert_groups/delete_alert_group.py
rootly_sdk/api/alert_groups/get_alert_group.py
rootly_sdk/api/alert_groups/list_alert_groups.py
rootly_sdk/api/alert_groups/update_alert_group.py
rootly_sdk/api/alert_routes/__init__.py
rootly_sdk/api/alert_routes/create_alert_route.py
rootly_sdk/api/alert_routes/delete_alert_route.py
rootly_sdk/api/alert_routes/get_alert_route.py
rootly_sdk/api/alert_routes/list_alert_routes.py
rootly_sdk/api/alert_routes/update_alert_route.py
rootly_sdk/api/alert_routing_rules/__init__.py
rootly_sdk/api/alert_routing_rules/create_alert_routing_rule.py
rootly_sdk/api/alert_routing_rules/delete_alert_routing_rule.py
rootly_sdk/api/alert_routing_rules/get_alert_routing_rule.py
rootly_sdk/api/alert_routing_rules/list_alert_routing_rules.py
rootly_sdk/api/alert_routing_rules/update_alert_routing_rule.py
rootly_sdk/api/alert_sources/__init__.py
rootly_sdk/api/alert_sources/create_alerts_source.py
rootly_sdk/api/alert_sources/delete_alerts_source.py
rootly_sdk/api/alert_sources/get_alerts_source.py
rootly_sdk/api/alert_sources/list_alerts_sources.py
rootly_sdk/api/alert_sources/update_alerts_source.py
