Metadata-Version: 2.4
Name: rootly
Version: 1.0.1
Summary: A client library for accessing Rootly API v1
License-Expression: Apache-2.0
Requires-Python: >=3.9
License-File: LICENSE
Requires-Dist: httpx<0.29.0,>=0.20.0
Requires-Dist: attrs>=22.2.0
Requires-Dist: python-dateutil>=2.8.0
Dynamic: license-file
